aternossuser.py
copied.py
lexica_arts.py
omlet_arcade_app.py
discordapiwebhooks/discordapiwebhooks.py
discordapiwebhooks/setup.py
phpdiscord/phpdiscord.py
omlet_arcade_bot-0.0.2.dist-info/METADATA
omlet_arcade_bot-0.0.2.dist-info/WHEEL
omlet_arcade_bot-0.0.2.dist-info/top_level.txt
omlet_arcade_bot-0.0.2.dist-info/RECORD
