Metadata-Version: 2.1
Name: omlet_arcade_bot
Version: 0.0.2
Summary: Модуль использующий, апи Omlet Arcade с 3-мя классами Auth, Bot и Power.
Home-page: UNKNOWN
License: UNKNOWN
Platform: UNKNOWN
